{
  "chunk-35ae34861d74b57c2816858f41990dee": {
    "tokens": 762,
    "content": "国语基本口径及规范\n1、【开头语】您好，XXX为您服务！请问有什么可以帮您！  【结束语】感谢您的来电，祝您生活愉快，再见！----感谢您的来电，麻烦您后期收到满意度相关的短信评价链接，给我们打个10分，感谢您的支持。祝您生活愉快，再见！\n\n2、查询或办理业务需客户等待时，“请您稍等，正在为您查询/办理”如果等待时间较久的，可说明：“请您稍等，正在为您查询，可能需要一点时间，麻烦您耐心等待一下”，等待结束后，需关怀客户，说声“感谢您的耐心等待”，再继续服务客户。(尽量避免离座咨询问题，必须要离座报备班长和支撑的话，记得点击“示忙”，避免客户挂机导致入线后的漏CALL)\n\n3、客户致电办理XX功能，若我处能直接为客户办理的，则必须询问客户是否了解XX的收费规则，若客户不了解，则为客户介绍；如我处不能直接受理，需转回XXX受理的，就无需询问客户是否了解资费。（注意：解答要严谨、完整，以免客户话费争议引起不必要的投诉）\n参加口径：您在韩国拨打回国内、在韩国接听和拨打韩国当地电话都是XXX元/分钟，拨打其他国家地区不含特定国家地区是XXX元/分钟，短信发回国内XXX元/条，发其他国家地区是XXX元/条，接收短信免费。\n\n4、办理XXX介绍参考口径：请问您对XXX的资费及使用规则了解吗？如客户了解无需介绍，不了解则介绍，举例：韩国XX3天XX元，办理成功立即扣费，当天使用生效算第一天，以北京时间自然天为一天计算，如不使用，套餐可保留XXX天.（解答不严谨、不完整，而导致客户争议，这个容易带来投诉风险，所以介绍资费必须完整，严谨）\n\n5、中途断线和中途无声，挂机后需回拨客户，如第一次未接通，继续回拨第二次，若2次都没有成功，则下发关怀短信给客户。入线无声先通话中询问客户是否听到，报三次口径后仍无声则挂机，挂机后马上回访一次，没成功则下发关怀短信。入线即断指10秒内自动断线且没有听到用户声音的，直接按来电归档即可，无需回访\n\n6、查询客户话费或通话中我们给客户提供话费信息，告知客户后，均需说明“余额仅供参考”\n\n7、对于客户询问了漫游地，但客户没有提供的，请展开二次询问。（参考口径：先生/女士，您好！为快速定位问题原因，便于产品的优化，请问您在哪个国家/地区？）\n\n8、当客户询问工号和姓名时候，我们可以报工号和姓，例如：我工号XXX，姓陈。如客户一直追问XXX办公地点是在哪里，统一解释是在中国大陆，最多只能提供到在广东，再引导客户咨询回业务问题。口径：您好，我们是在中国大陆办公的，但无论我们身在何方，都会用心为您服务的，请问还有什么业务问题可以帮到您呢？",
    "chunk_order_index": 0,
    "full_doc_id": "doc-35ae34861d74b57c2816858f41990dee",
    "file_path": "/mnt/sdb/TuRan/Project/RagDeepSeek/data/10086.txt"
  }
}